main.py
xuew-0.1.0.dist-info/METADATA
xuew-0.1.0.dist-info/WHEEL
xuew-0.1.0.dist-info/top_level.txt
xuew-0.1.0.dist-info/RECORD
