Metadata-Version: 2.4
Name: xuew
Version: 0.1.0
Summary: Add your description here
Requires-Python: >=3.11
Requires-Dist: beswarm>=0.1.16
